radcalnet/__init__.py
radcalnet/daily_file.py
radcalnet/data_store.py
radcalnet/file_handle.py
radcalnet/site_measurements.py
radcalnet-0.1.2.dist-info/METADATA
radcalnet-0.1.2.dist-info/RECORD
radcalnet-0.1.2.dist-info/WHEEL
radcalnet-0.1.2.dist-info/top_level.txt
