Metadata-Version: 2.1
Name: radcalnet
Version: 0.1.2
Summary: Python package for easy access to the measurements published by RadCalNet.org
Home-page: https://github.com/satellogic/radcalnet
Author: Slava Kerner, Amit Aronovitch
Author-email: amit@satellogic.com
License: UNKNOWN
Platform: UNKNOWN
Classifier: Development Status :: 4 - Beta
Classifier: Environment :: Console
Classifier: Intended Audience :: Science/Research
Classifier: Operating System :: OS Independent
Classifier: Programming Language :: Python :: 3
Classifier: Topic :: Software Development :: Libraries :: Python Modules
Classifier: Topic :: Utilities
Requires-Dist: pandas
Requires-Dist: matplotlib
